DeskAutomation/__init__.py
deskautomation-1.0.3.dist-info/METADATA
deskautomation-1.0.3.dist-info/WHEEL
deskautomation-1.0.3.dist-info/top_level.txt
deskautomation-1.0.3.dist-info/RECORD
