Metadata-Version: 2.4
Name: deskautomation
Version: 1.0.3
Summary: A library for desktop automation using PyAutoGUI and OCR.
Author: Mehabalan
Author-email: majesticmehabalan@gmail.com
Classifier: Programming Language :: Python :: 3
Classifier: License :: OSI Approved :: MIT License
Classifier: Operating System :: OS Independent
Requires-Python: >=3.6
Requires-Dist: pyautogui
Requires-Dist: pytesseract
Requires-Dist: pygetwindow
Requires-Dist: Pillow
Requires-Dist: opencv-python
Dynamic: author
Dynamic: author-email
Dynamic: classifier
Dynamic: requires-dist
Dynamic: requires-python
Dynamic: summary
